sparse/__init__.py
sparse/array_api.py
sparse/core.py
pysparse_array-1.0.9.dist-info/LICENSE.txt
pysparse_array-1.0.9.dist-info/METADATA
pysparse_array-1.0.9.dist-info/WHEEL
pysparse_array-1.0.9.dist-info/top_level.txt
pysparse_array-1.0.9.dist-info/RECORD
