Metadata-Version: 2.1
Name: pysparse-array
Version: 1.0.9
Summary: A package that enables on-the-fly encoding and decoding of large NumPy arrays as Sparse binaries.
Home-page: https://github.com/tdgfrost/PySparse
Download-URL: https://pypi.org/project/pysparse-array/
Author: Thomas Frost
Author-email: Thomas Frost <tdgfrost@gmail.com>
Project-URL: Homepage, https://github.com/tdgfrost/PySparse
Project-URL: Bug Tracker, https://github.com/tdgfrost/PySparse/issues
Classifier: Programming Language :: Python :: 3
Classifier: License :: OSI Approved :: MIT License
Classifier: Operating System :: OS Independent
Requires-Python: >=3.8.0
License-File: LICENSE.txt
Requires-Dist: numpy >=1.18.0
Requires-Dist: numba >=0.49.0
